botbuilder/azure/__init__.py
botbuilder/azure/about.py
botbuilder/azure/azure_queue_storage.py
botbuilder/azure/blob_storage.py
botbuilder/azure/cosmosdb_partitioned_storage.py
botbuilder_azure-4.17.1.dist-info/METADATA
botbuilder_azure-4.17.1.dist-info/WHEEL
botbuilder_azure-4.17.1.dist-info/top_level.txt
botbuilder_azure-4.17.1.dist-info/RECORD
