Metadata-Version: 2.1
Name: botbuilder-azure
Version: 4.17.1
Summary: Microsoft Bot Framework Bot Builder
Home-page: https://www.github.com/Microsoft/botbuilder-python
Author: Microsoft
License: MIT
Keywords: BotBuilderAzure,bots,ai,botframework,botbuilder,azure
Classifier: Programming Language :: Python :: 3.7
Classifier: Intended Audience :: Developers
Classifier: License :: OSI Approved :: MIT License
Classifier: Operating System :: OS Independent
Classifier: Development Status :: 5 - Production/Stable
Classifier: Topic :: Scientific/Engineering :: Artificial Intelligence
Requires-Dist: azure-cosmos==4.7.0
Requires-Dist: azure-storage-blob==12.7.0
Requires-Dist: azure-storage-queue==12.4.0
Requires-Dist: botbuilder-schema==4.17.1
Requires-Dist: botframework-connector==4.17.1
Requires-Dist: jsonpickle<4,>=1.2
Requires-Dist: aiounittest==1.3.0
